llm_canvas/__init__.py
llm_canvas/canvas.py
llm_canvas/canvas_client.py
llm_canvas/canvas_registry.py
llm_canvas/types.py
llm_canvas/_server/__init__.py
llm_canvas/_server/_api.py
llm_canvas/_server/_cli.py
llm_canvas/_server/_events.py
llm_canvas/_server/_registry.py
llm_canvas/_server/_server.py
llm_canvas/_server/_types.py
llm_canvas/_server/static/404.html
llm_canvas/_server/static/index.html
llm_canvas/_server/static/assets/index-KZ3X4Ax6.css
llm_canvas/_server/static/assets/index-oCARlKtp.js
llm_canvas/_server/static/assets/logo-icon-badge.svg
llm_canvas/_server/static/assets/logo-icon-dark.svg
llm_canvas/_server/static/assets/logo-icon-light.svg
llm_canvas_generated_client/.gitignore
llm_canvas_generated_client/README.md
llm_canvas_generated_client/__init__.py
llm_canvas_generated_client/pyproject.toml
llm_canvas_generated_client/llm_canvas_api_client/__init__.py
llm_canvas_generated_client/llm_canvas_api_client/client.py
llm_canvas_generated_client/llm_canvas_api_client/errors.py
llm_canvas_generated_client/llm_canvas_api_client/py.typed
llm_canvas_generated_client/llm_canvas_api_client/types.py
llm_canvas_generated_client/llm_canvas_api_client/api/__init__.py
llm_canvas_generated_client/llm_canvas_api_client/api/v1/__init__.py
llm_canvas_generated_client/llm_canvas_api_client/api/v1/canvas_message_sse_api_v1_canvas_canvas_id_sse_get.py
llm_canvas_generated_client/llm_canvas_api_client/api/v1/canvas_sse_api_v1_canvas_sse_get.py
llm_canvas_generated_client/llm_canvas_api_client/api/v1/commit_message_api_v1_canvas_canvas_id_messages_post.py
llm_canvas_generated_client/llm_canvas_api_client/api/v1/create_canvas_api_v1_canvas_post.py
llm_canvas_generated_client/llm_canvas_api_client/api/v1/delete_canvas_api_v1_canvas_canvas_id_delete.py
llm_canvas_generated_client/llm_canvas_api_client/api/v1/get_canvas_api_v1_canvas_get.py
llm_canvas_generated_client/llm_canvas_api_client/api/v1/health_check_api_v1_health_get.py
llm_canvas-0.2.2.dist-info/METADATA
llm_canvas-0.2.2.dist-info/WHEEL
llm_canvas-0.2.2.dist-info/entry_points.txt
llm_canvas-0.2.2.dist-info/RECORD
