Metadata-Version: 2.1
Name: llm-canvas
Version: 0.2.2
Summary: Visualize complex LLM conversation flows in infinite canvases
Project-URL: Homepage, https://github.com/LittleLittleCloud/llm_canvas
Author: LittleLittleCloud
License: MIT
Keywords: ai,chat,llm,visualization
Classifier: Intended Audience :: Developers
Classifier: License :: OSI Approved :: MIT License
Classifier: Programming Language :: Python :: 3
Requires-Python: >=3.9
Requires-Dist: anthropic>=0.62.0
Requires-Dist: fastapi>=0.110.0
Requires-Dist: openai>=1.99.5
Requires-Dist: typing-extensions>=4.0.0; python_version < '3.11'
Requires-Dist: uvicorn[standard]>=0.29.0
Provides-Extra: client
Provides-Extra: dev
Requires-Dist: black; extra == 'dev'
Requires-Dist: mypy; extra == 'dev'
Requires-Dist: pytest>=7.0; extra == 'dev'
Requires-Dist: ruff; extra == 'dev'
Provides-Extra: server
Requires-Dist: uvicorn[standard]>=0.29.0; extra == 'server'
